pyanimals/__init__.py
pyanimals-0.1.4.dist-info/WHEEL
pyanimals-0.1.4.dist-info/METADATA
pyanimals-0.1.4.dist-info/RECORD
